cartotool/__init__.py
cartotool/api_client.py
cartotool/configuration.py
cartotool/exceptions.py
cartotool/rest.py
cartotool/api/__init__.py
cartotool/api/data_cell_controller_api.py
cartotool/api/data_collection_controller_api.py
cartotool/api/data_tile_controller_api.py
cartotool/api/icon_controller_api.py
cartotool/api/layer_bitmap_controller_api.py
cartotool/api/layer_controller_api.py
cartotool/api/layer_group_controller_api.py
cartotool/api/layer_linked_controller_api.py
cartotool/api/layer_tms_controller_api.py
cartotool/api/layer_vector_controller_api.py
cartotool/api/layer_wms_controller_api.py
cartotool/api/map_controller_api.py
cartotool/api/project_controller_api.py
cartotool/api/story_controller_api.py
cartotool/api/user_account_controller_api.py
cartotool/api/user_authority_controller_api.py
cartotool/api/user_controller_api.py
cartotool/api/user_group_controller_api.py
cartotool/api/user_status_controller_api.py
cartotool/api/workspace_controller_api.py
cartotool/models/__init__.py
cartotool/models/data_cell_form.py
cartotool/models/data_collection.py
cartotool/models/data_collection_form.py
cartotool/models/data_collection_geometry.py
cartotool/models/inline_object.py
cartotool/models/key_revoke_form.py
cartotool/models/layer.py
cartotool/models/layer_bitmap.py
cartotool/models/layer_bitmap_form.py
cartotool/models/layer_dashboard.py
cartotool/models/layer_group.py
cartotool/models/layer_group_form.py
cartotool/models/layer_linked_form.py
cartotool/models/layer_move_form.py
cartotool/models/layer_style_point.py
cartotool/models/layer_style_polygon.py
cartotool/models/layer_tms_form.py
cartotool/models/layer_vector_form.py
cartotool/models/layer_wms_form.py
cartotool/models/layer_wrapper.py
cartotool/models/pageable.py
cartotool/models/password_reset_form.py
cartotool/models/project.py
cartotool/models/project_form.py
cartotool/models/project_image.py
cartotool/models/request_password_reset.py
cartotool/models/status.py
cartotool/models/story.py
cartotool_cartotool_dev-1.0.6.dist-info/LICENSE
cartotool_cartotool_dev-1.0.6.dist-info/METADATA
cartotool_cartotool_dev-1.0.6.dist-info/WHEEL
cartotool_cartotool_dev-1.0.6.dist-info/top_level.txt
cartotool_cartotool_dev-1.0.6.dist-info/RECORD
